JAWGF/__init__.py
JAWGF/fusion.py
jawgf-0.1.0.dist-info/licenses/LICENSE
jawgf-0.1.0.dist-info/METADATA
jawgf-0.1.0.dist-info/WHEEL
jawgf-0.1.0.dist-info/top_level.txt
jawgf-0.1.0.dist-info/RECORD
