Metadata-Version: 2.4
Name: JAWGF
Version: 0.1.0
Summary: Joint auto-weighted graph fusion and scalable semi-supervised learning
Author-email: James McIntyre <mcintyre.james.anthony@gmail.com>
License: MIT
Project-URL: Homepage, https://github.com/James-Mc1ntyre/JAWGF
Project-URL: Source, https://github.com/James-Mc1ntyre/JAWGF
Requires-Python: >=3.9
License-File: LICENSE
Requires-Dist: numpy
Requires-Dist: scipy
Requires-Dist: scikit-learn
Dynamic: license-file
